boomstick/__init__.py
boomstick/boomstick.py
Boomstick-1.1.dist-info/LICENSE.md
Boomstick-1.1.dist-info/METADATA
Boomstick-1.1.dist-info/WHEEL
Boomstick-1.1.dist-info/top_level.txt
Boomstick-1.1.dist-info/RECORD
