Metadata-Version: 2.1
Name: Boomstick
Version: 1.1
Summary: UNKNOWN
Home-page: https://github.com/FuelRats/boomstick
Author: The Fuel Rats Mischief
Author-email: UNKNOWN
License: BSD-3-Clause
Platform: UNKNOWN
Classifier: Programming Language :: Python :: 3
Classifier: License :: OSI Approved :: BSD License
Classifier: Operating System :: OS Independent
Classifier: Development Status :: 5 - Production/Stable
Classifier: Intended Audience :: Developers
Requires-Dist: coloredlogs
